mupemenet/App.py
mupemenet/__init__.py
mupemenet-0.1.dist-info/LICENSE.txt
mupemenet-0.1.dist-info/METADATA
mupemenet-0.1.dist-info/WHEEL
mupemenet-0.1.dist-info/entry_points.txt
mupemenet-0.1.dist-info/top_level.txt
mupemenet-0.1.dist-info/RECORD
